odoo10_addon_base_location_nuts-10.0.1.0.0-py2.7-nspkg.pth
odoo/addons/base_location_nuts/README.rst
odoo/addons/base_location_nuts/__init__.py
odoo/addons/base_location_nuts/__manifest__.py
odoo/addons/base_location_nuts/i18n/de.po
odoo/addons/base_location_nuts/i18n/es.po
odoo/addons/base_location_nuts/i18n/fi.po
odoo/addons/base_location_nuts/i18n/it.po
odoo/addons/base_location_nuts/i18n/sl.po
odoo/addons/base_location_nuts/images/new_fields.png
odoo/addons/base_location_nuts/models/__init__.py
odoo/addons/base_location_nuts/models/res_country.py
odoo/addons/base_location_nuts/models/res_partner.py
odoo/addons/base_location_nuts/models/res_partner_nuts.py
odoo/addons/base_location_nuts/security/ir.model.access.csv
odoo/addons/base_location_nuts/static/description/icon.png
odoo/addons/base_location_nuts/tests/__init__.py
odoo/addons/base_location_nuts/tests/test_base_location_nuts.py
odoo/addons/base_location_nuts/views/res_country_view.xml
odoo/addons/base_location_nuts/views/res_partner_nuts_view.xml
odoo/addons/base_location_nuts/views/res_partner_view.xml
odoo/addons/base_location_nuts/wizard/__init__.py
odoo/addons/base_location_nuts/wizard/nuts_import.py
odoo/addons/base_location_nuts/wizard/nuts_import_view.xml
odoo10_addon_base_location_nuts-10.0.1.0.0.dist-info/DESCRIPTION.rst
odoo10_addon_base_location_nuts-10.0.1.0.0.dist-info/METADATA
odoo10_addon_base_location_nuts-10.0.1.0.0.dist-info/RECORD
odoo10_addon_base_location_nuts-10.0.1.0.0.dist-info/WHEEL
odoo10_addon_base_location_nuts-10.0.1.0.0.dist-info/metadata.json
odoo10_addon_base_location_nuts-10.0.1.0.0.dist-info/namespace_packages.txt
odoo10_addon_base_location_nuts-10.0.1.0.0.dist-info/top_level.txt
